imp.py
zombie_imp/__init__.py
zombie_imp/imp_3_11.py
zombie_imp/pkgutil.py
zombie_imp-0.0.4.dist-info/licenses/LICENSE
zombie_imp-0.0.4.dist-info/METADATA
zombie_imp-0.0.4.dist-info/WHEEL
zombie_imp-0.0.4.dist-info/top_level.txt
zombie_imp-0.0.4.dist-info/RECORD
