Metadata-Version: 2.4
Name: zombie-imp
Version: 0.0.4
Summary: A copy of the `imp` module that was removed in Python 3.12
Maintainer-email: Petr Viktorin <encukou@gmail.com>
Project-URL: Homepage, https://github.com/encukou/zombie-imp
Project-URL: Bug Tracker, https://github.com/encukou/zombie-imp/issues
Classifier: Programming Language :: Python :: 3
Classifier: License :: OSI Approved :: Python Software Foundation License
Classifier: Operating System :: OS Independent
Requires-Python: >=3.7
License-File: LICENSE
Dynamic: license-file
